roddy/__init__.py
roddy-0.0.1.dist-info/METADATA
roddy-0.0.1.dist-info/RECORD
roddy-0.0.1.dist-info/WHEEL
roddy-0.0.1.dist-info/entry_points.txt
roddy-0.0.1.dist-info/top_level.txt
